<annotaion>
  <folder>Train_Jpegs</folder>
  <filename>30948.jpg</filename>
  <path>D:\Bosch Dataset\Train\Rgb\Train_Jpegs\30948.jpg</path>
  <size>
    <width>800</width>
    <height>600</height>
    <depth>3</depth>
  </size>
  <segmented>0</segmented>
  <object>
    <name>Green</name>
    <pose>Unspecified</pose>
    <occluded>False</occluded>
    <difficult>0</difficult>
    <bndbox>
      <xmin>512.191</xmin>
      <ymin>234.669</ymin>
      <xmax>520.242</xmax>
      <ymax>248.174</ymax>
    </bndbox>
  </object>
  <object>
    <name>Green</name>
    <pose>Unspecified</pose>
    <occluded>False</occluded>
    <difficult>0</difficult>
    <bndbox>
      <xmin>499.607</xmin>
      <ymin>240.037</ymin>
      <xmax>507.23</xmax>
      <ymax>251.845</ymax>
    </bndbox>
  </object>
  <object>
    <name>Green</name>
    <pose>Unspecified</pose>
    <occluded>False</occluded>
    <difficult>0</difficult>
    <bndbox>
      <xmin>435.484</xmin>
      <ymin>207.453</ymin>
      <xmax>444.303</xmax>
      <ymax>224.642</ymax>
    </bndbox>
  </object>
  <object>
    <name>Red</name>
    <pose>Unspecified</pose>
    <occluded>False</occluded>
    <difficult>0</difficult>
    <bndbox>
      <xmin>318.367</xmin>
      <ymin>239.48</ymin>
      <xmax>325.623</xmax>
      <ymax>253.085</ymax>
    </bndbox>
  </object>
  <object>
    <name>Red</name>
    <pose>Unspecified</pose>
    <occluded>False</occluded>
    <difficult>0</difficult>
    <bndbox>
      <xmin>357.822</xmin>
      <ymin>247.416</ymin>
      <xmax>362.583</xmax>
      <ymax>255.239</ymax>
    </bndbox>
  </object>
</annotaion>
