<annotation>
  <folder>Train_Jpegs</folder>
  <filename>500538.jpg</filename>
  <path>D:\Bosch Dataset\Train\Rgb\Train_Jpegs\500538.jpg</path>
  <size>
    <width>800</width>
    <height>600</height>
    <depth>3</depth>
  </size>
  <segmented>0</segmented>
  <object>
    <name>Red</name>
    <pose>Unspecified</pose>
    <occluded>False</occluded>
    <difficult>0</difficult>
    <bndbox>
      <xmin>28.19</xmin>
      <ymin>177.099</ymin>
      <xmax>35.855</xmax>
      <ymax>197.537</ymax>
    </bndbox>
  </object>
  <object>
    <name>Red</name>
    <pose>Unspecified</pose>
    <occluded>False</occluded>
    <difficult>0</difficult>
    <bndbox>
      <xmin>640.174</xmin>
      <ymin>150.55</ymin>
      <xmax>664.247</xmax>
      <ymax>192.49</ymax>
    </bndbox>
  </object>
  <object>
    <name>Red</name>
    <pose>Unspecified</pose>
    <occluded>False</occluded>
    <difficult>0</difficult>
    <bndbox>
      <xmin>517.553</xmin>
      <ymin>183.651</ymin>
      <xmax>528.837</xmax>
      <ymax>203.21</ymax>
    </bndbox>
  </object>
  <object>
    <name>Red</name>
    <pose>Unspecified</pose>
    <occluded>False</occluded>
    <difficult>0</difficult>
    <bndbox>
      <xmin>362.835</xmin>
      <ymin>131.327</ymin>
      <xmax>373.903</xmax>
      <ymax>154.925</ymax>
    </bndbox>
  </object>
</annotation>
