<annotaion>
  <folder>Train_Jpegs</folder>
  <filename>538150.jpg</filename>
  <path>D:\Bosch Dataset\Train\Rgb\Train_Jpegs\538150.jpg</path>
  <size>
    <width>800</width>
    <height>600</height>
    <depth>3</depth>
  </size>
  <segmented>0</segmented>
  <object>
    <name>Red</name>
    <pose>Unspecified</pose>
    <occluded>False</occluded>
    <difficult>0</difficult>
    <bndbox>
      <xmin>351.236</xmin>
      <ymin>232.279</ymin>
      <xmax>356.27</xmax>
      <ymax>245.106</ymax>
    </bndbox>
  </object>
  <object>
    <name>Red</name>
    <pose>Unspecified</pose>
    <occluded>False</occluded>
    <difficult>0</difficult>
    <bndbox>
      <xmin>408.061</xmin>
      <ymin>234.348</ymin>
      <xmax>413.234</xmax>
      <ymax>246.554</ymax>
    </bndbox>
  </object>
  <object>
    <name>Red</name>
    <pose>Unspecified</pose>
    <occluded>False</occluded>
    <difficult>0</difficult>
    <bndbox>
      <xmin>483.883</xmin>
      <ymin>245.895</ymin>
      <xmax>489.423</xmax>
      <ymax>260.133</ymax>
    </bndbox>
  </object>
  <object>
    <name>Red</name>
    <pose>Unspecified</pose>
    <occluded>False</occluded>
    <difficult>0</difficult>
    <bndbox>
      <xmin>525.628</xmin>
      <ymin>266.277</ymin>
      <xmax>533.459</xmax>
      <ymax>280.563</ymax>
    </bndbox>
  </object>
  <object>
    <name>Red</name>
    <pose>Unspecified</pose>
    <occluded>False</occluded>
    <difficult>0</difficult>
    <bndbox>
      <xmin>593.078</xmin>
      <ymin>257.891</ymin>
      <xmax>600.112</xmax>
      <ymax>272.617</ymax>
    </bndbox>
  </object>
</annotaion>
