<annotation>
  <folder>Train_Jpegs</folder>
  <filename>581148.jpg</filename>
  <path>D:\Bosch Dataset\Train\Rgb\Train_Jpegs\581148.jpg</path>
  <size>
    <width>800</width>
    <height>600</height>
    <depth>3</depth>
  </size>
  <segmented>0</segmented>
  <object>
    <name>Green</name>
    <pose>Unspecified</pose>
    <occluded>False</occluded>
    <difficult>0</difficult>
    <bndbox>
      <xmin>505.865</xmin>
      <ymin>194.964</ymin>
      <xmax>519.13</xmax>
      <ymax>222.853</ymax>
    </bndbox>
  </object>
  <object>
    <name>Green</name>
    <pose>Unspecified</pose>
    <occluded>False</occluded>
    <difficult>0</difficult>
    <bndbox>
      <xmin>374.723</xmin>
      <ymin>211.791</ymin>
      <xmax>383.764</xmax>
      <ymax>231.425</ymax>
    </bndbox>
  </object>
  <object>
    <name>Green</name>
    <pose>Unspecified</pose>
    <occluded>False</occluded>
    <difficult>0</difficult>
    <bndbox>
      <xmin>272.962</xmin>
      <ymin>157.847</ymin>
      <xmax>281.985</xmax>
      <ymax>178.412</ymax>
    </bndbox>
  </object>
  <object>
    <name>Green</name>
    <pose>Unspecified</pose>
    <occluded>False</occluded>
    <difficult>0</difficult>
    <bndbox>
      <xmin>198.989</xmin>
      <ymin>143.157</ymin>
      <xmax>207.803</xmax>
      <ymax>164.142</ymax>
    </bndbox>
  </object>
  <object>
    <name>Red</name>
    <pose>Unspecified</pose>
    <occluded>False</occluded>
    <difficult>0</difficult>
    <bndbox>
      <xmin>122.207</xmin>
      <ymin>134.881</ymin>
      <xmax>130.617</xmax>
      <ymax>156.517</ymax>
    </bndbox>
  </object>
</annotation>
