<annotaion>
  <folder>Train_Jpegs</folder>
  <filename>29916.jpg</filename>
  <path>D:\Bosch Dataset\Train\Rgb\Train_Jpegs\29916.jpg</path>
  <size>
    <width>800</width>
    <height>600</height>
    <depth>3</depth>
  </size>
  <segmented>0</segmented>
  <object>
    <name>Red</name>
    <pose>Unspecified</pose>
    <occluded>False</occluded>
    <difficult>0</difficult>
    <bndbox>
      <xmin>356.849</xmin>
      <ymin>274.947</ymin>
      <xmax>365.232</xmax>
      <ymax>298.626</ymax>
    </bndbox>
  </object>
  <object>
    <name>Red</name>
    <pose>Unspecified</pose>
    <occluded>False</occluded>
    <difficult>0</difficult>
    <bndbox>
      <xmin>538.476</xmin>
      <ymin>229.411</ymin>
      <xmax>542.778</xmax>
      <ymax>240.679</ymax>
    </bndbox>
  </object>
  <object>
    <name>Red</name>
    <pose>Unspecified</pose>
    <occluded>True</occluded>
    <difficult>0</difficult>
    <bndbox>
      <xmin>603.996</xmin>
      <ymin>264.931</ymin>
      <xmax>607.723</xmax>
      <ymax>273.507</ymax>
    </bndbox>
  </object>
  <object>
    <name>Red</name>
    <pose>Unspecified</pose>
    <occluded>True</occluded>
    <difficult>0</difficult>
    <bndbox>
      <xmin>688.924</xmin>
      <ymin>249.071</ymin>
      <xmax>696.72</xmax>
      <ymax>270.007</ymax>
    </bndbox>
  </object>
</annotaion>
