<annotation>
  <folder>Train_Jpegs</folder>
  <filename>30600.jpg</filename>
  <path>D:\Bosch Dataset\Train\Rgb\Train_Jpegs\30600.jpg</path>
  <size>
    <width>800</width>
    <height>600</height>
    <depth>3</depth>
  </size>
  <segmented>0</segmented>
  <object>
    <name>Red</name>
    <pose>Unspecified</pose>
    <occluded>False</occluded>
    <difficult>0</difficult>
    <bndbox>
      <xmin>367.118</xmin>
      <ymin>227.732</ymin>
      <xmax>373.696</xmax>
      <ymax>239.135</ymax>
    </bndbox>
  </object>
  <object>
    <name>Yellow</name>
    <pose>Unspecified</pose>
    <occluded>False</occluded>
    <difficult>0</difficult>
    <bndbox>
      <xmin>327.647</xmin>
      <ymin>245.055</ymin>
      <xmax>333.787</xmax>
      <ymax>251.853</ymax>
    </bndbox>
  </object>
  <object>
    <name>Yellow</name>
    <pose>Unspecified</pose>
    <occluded>False</occluded>
    <difficult>0</difficult>
    <bndbox>
      <xmin>298.512</xmin>
      <ymin>244.995</ymin>
      <xmax>302.358</xmax>
      <ymax>250.847</ymax>
    </bndbox>
  </object>
  <object>
    <name>Yellow</name>
    <pose>Unspecified</pose>
    <occluded>False</occluded>
    <difficult>0</difficult>
    <bndbox>
      <xmin>310.384</xmin>
      <ymin>244.828</ymin>
      <xmax>316.571</xmax>
      <ymax>250.847</ymax>
    </bndbox>
  </object>
  <object>
    <name>Red</name>
    <pose>Unspecified</pose>
    <occluded>False</occluded>
    <difficult>0</difficult>
    <bndbox>
      <xmin>263.38</xmin>
      <ymin>254.693</ymin>
      <xmax>269.508</xmax>
      <ymax>265.007</ymax>
    </bndbox>
  </object>
</annotation>
