<annotation>
  <folder>Train_Jpegs</folder>
  <filename>451642.jpg</filename>
  <path>D:\Bosch Dataset\Train\Rgb\Train_Jpegs\451642.jpg</path>
  <size>
    <width>800</width>
    <height>600</height>
    <depth>3</depth>
  </size>
  <segmented>0</segmented>
  <object>
    <name>Red</name>
    <pose>Unspecified</pose>
    <occluded>False</occluded>
    <difficult>0</difficult>
    <bndbox>
      <xmin>780.58</xmin>
      <ymin>157.453</ymin>
      <xmax>799.718</xmax>
      <ymax>205.094</ymax>
    </bndbox>
  </object>
  <object>
    <name>Red</name>
    <pose>Unspecified</pose>
    <occluded>False</occluded>
    <difficult>0</difficult>
    <bndbox>
      <xmin>653.647</xmin>
      <ymin>206.829</ymin>
      <xmax>667.225</xmax>
      <ymax>238.924</ymax>
    </bndbox>
  </object>
  <object>
    <name>Red</name>
    <pose>Unspecified</pose>
    <occluded>False</occluded>
    <difficult>0</difficult>
    <bndbox>
      <xmin>489.477</xmin>
      <ymin>147.241</ymin>
      <xmax>501.318</xmax>
      <ymax>174.432</ymax>
    </bndbox>
  </object>
  <object>
    <name>Red</name>
    <pose>Unspecified</pose>
    <occluded>False</occluded>
    <difficult>0</difficult>
    <bndbox>
      <xmin>388.607</xmin>
      <ymin>141.32</ymin>
      <xmax>402.202</xmax>
      <ymax>170.704</ymax>
    </bndbox>
  </object>
</annotation>
