<annotation>
  <folder>Train_Jpegs</folder>
  <filename>706594.jpg</filename>
  <path>D:\Bosch Dataset\Train\Rgb\Train_Jpegs\706594.jpg</path>
  <size>
    <width>800</width>
    <height>600</height>
    <depth>3</depth>
  </size>
  <segmented>0</segmented>
  <object>
    <name>Red</name>
    <pose>Unspecified</pose>
    <occluded>False</occluded>
    <difficult>0</difficult>
    <bndbox>
      <xmin>174.636</xmin>
      <ymin>211.958</ymin>
      <xmax>180.002</xmax>
      <ymax>224.528</ymax>
    </bndbox>
  </object>
  <object>
    <name>Red</name>
    <pose>Unspecified</pose>
    <occluded>False</occluded>
    <difficult>0</difficult>
    <bndbox>
      <xmin>214.901</xmin>
      <ymin>217.872</ymin>
      <xmax>219.133</xmax>
      <ymax>229.199</ymax>
    </bndbox>
  </object>
  <object>
    <name>Red</name>
    <pose>Unspecified</pose>
    <occluded>False</occluded>
    <difficult>0</difficult>
    <bndbox>
      <xmin>119.352</xmin>
      <ymin>210.407</ymin>
      <xmax>124.963</xmax>
      <ymax>223.768</ymax>
    </bndbox>
  </object>
  <object>
    <name>Red</name>
    <pose>Unspecified</pose>
    <occluded>False</occluded>
    <difficult>0</difficult>
    <bndbox>
      <xmin>318.841</xmin>
      <ymin>240.186</ymin>
      <xmax>324.905</xmax>
      <ymax>252.987</ymax>
    </bndbox>
  </object>
</annotation>
