<annotation verified="yes">
	<folder>sim_image</folder>
	<filename>frame1208.jpg</filename>
	<path>C:\Users\mstei\Downloads\Capstone\sim_image\frame1208.jpg</path>
	<source>
		<database>Unknown</database>
	</source>
	<size>
		<width>800</width>
		<height>600</height>
		<depth>3</depth>
	</size>
	<segmented>0</segmented>
	<object>
		<name>Green</name>
		<pose>Unspecified</pose>
		<truncated>0</truncated>
		<difficult>0</difficult>
		<bndbox>
			<xmin>671</xmin>
			<ymin>219</ymin>
			<xmax>711</xmax>
			<ymax>304</ymax>
		</bndbox>
	</object>
	<object>
		<name>Green</name>
		<pose>Unspecified</pose>
		<truncated>0</truncated>
		<difficult>0</difficult>
		<bndbox>
			<xmin>515</xmin>
			<ymin>223</ymin>
			<xmax>549</xmax>
			<ymax>304</ymax>
		</bndbox>
	</object>
</annotation>
