<annotation verified="yes">
	<folder>sim_image</folder>
	<filename>frame611.jpg</filename>
	<path>C:\Users\mstei\Downloads\Capstone\sim_image\frame611.jpg</path>
	<source>
		<database>Unknown</database>
	</source>
	<size>
		<width>800</width>
		<height>600</height>
		<depth>3</depth>
	</size>
	<segmented>0</segmented>
	<object>
		<name>Red</name>
		<pose>Unspecified</pose>
		<truncated>0</truncated>
		<difficult>0</difficult>
		<bndbox>
			<xmin>7</xmin>
			<ymin>20</ymin>
			<xmax>79</xmax>
			<ymax>190</ymax>
		</bndbox>
	</object>
	<object>
		<name>Red</name>
		<pose>Unspecified</pose>
		<truncated>0</truncated>
		<difficult>0</difficult>
		<bndbox>
			<xmin>321</xmin>
			<ymin>18</ymin>
			<xmax>397</xmax>
			<ymax>187</ymax>
		</bndbox>
	</object>
	<object>
		<name>Red</name>
		<pose>Unspecified</pose>
		<truncated>0</truncated>
		<difficult>0</difficult>
		<bndbox>
			<xmin>641</xmin>
			<ymin>13</ymin>
			<xmax>721</xmax>
			<ymax>187</ymax>
		</bndbox>
	</object>
</annotation>
