<annotation verified="yes">
	<folder>sim_image</folder>
	<filename>frame1548.jpg</filename>
	<path>C:\Users\mstei\Downloads\Capstone\sim_image\frame1548.jpg</path>
	<source>
		<database>Unknown</database>
	</source>
	<size>
		<width>800</width>
		<height>600</height>
		<depth>3</depth>
	</size>
	<segmented>0</segmented>
	<object>
		<name>Yellow</name>
		<pose>Unspecified</pose>
		<truncated>0</truncated>
		<difficult>0</difficult>
		<bndbox>
			<xmin>630</xmin>
			<ymin>216</ymin>
			<xmax>674</xmax>
			<ymax>315</ymax>
		</bndbox>
	</object>
	<object>
		<name>Yellow</name>
		<pose>Unspecified</pose>
		<truncated>0</truncated>
		<difficult>0</difficult>
		<bndbox>
			<xmin>444</xmin>
			<ymin>218</ymin>
			<xmax>487</xmax>
			<ymax>314</ymax>
		</bndbox>
	</object>
	<object>
		<name>Yellow</name>
		<pose>Unspecified</pose>
		<truncated>0</truncated>
		<difficult>0</difficult>
		<bndbox>
			<xmin>256</xmin>
			<ymin>218</ymin>
			<xmax>301</xmax>
			<ymax>315</ymax>
		</bndbox>
	</object>
</annotation>
