<annotation verified="yes">
	<folder>sim_image</folder>
	<filename>frame369.jpg</filename>
	<path>C:\Users\mstei\Downloads\Capstone\sim_image\frame369.jpg</path>
	<source>
		<database>Unknown</database>
	</source>
	<size>
		<width>800</width>
		<height>600</height>
		<depth>3</depth>
	</size>
	<segmented>0</segmented>
	<object>
		<name>Red</name>
		<pose>Unspecified</pose>
		<truncated>0</truncated>
		<difficult>0</difficult>
		<bndbox>
			<xmin>456</xmin>
			<ymin>368</ymin>
			<xmax>480</xmax>
			<ymax>426</ymax>
		</bndbox>
	</object>
	<object>
		<name>Red</name>
		<pose>Unspecified</pose>
		<truncated>0</truncated>
		<difficult>0</difficult>
		<bndbox>
			<xmin>566</xmin>
			<ymin>367</ymin>
			<xmax>593</xmax>
			<ymax>428</ymax>
		</bndbox>
	</object>
	<object>
		<name>Red</name>
		<pose>Unspecified</pose>
		<truncated>0</truncated>
		<difficult>0</difficult>
		<bndbox>
			<xmin>682</xmin>
			<ymin>366</ymin>
			<xmax>711</xmax>
			<ymax>427</ymax>
		</bndbox>
	</object>
</annotation>
